hooks/__init__.py
hooks/yeedu.py
operators/__init__.py
operators/yeedu.py
PrefectJobRunOperatorTest-0.0.8.dist-info/METADATA
PrefectJobRunOperatorTest-0.0.8.dist-info/WHEEL
PrefectJobRunOperatorTest-0.0.8.dist-info/top_level.txt
PrefectJobRunOperatorTest-0.0.8.dist-info/RECORD
