Metadata-Version: 2.1
Name: PrefectJobRunOperatorTest
Version: 0.0.8
Summary: Submission and monitoring of jobs and notebooks using the Yeedu API in prefect. 
Author: pravallika
Author-email: pravallika.akumuri@modak.com
License: All Rights Reserved
Requires-Dist: requests >=2.27
Requires-Dist: websocket-client >=1.8.0
Requires-Dist: rel >=0.4.9.19
